{
    "users": [
        {
            "id": "47125423",
            "name": "Marilou Goldner PhD",
            "phone": "(657) 984-4352",
            "email": "Alysha88@yahoo.com"
        },
        {
            "id": "90624632",
            "name": "Candelario Heaney",
            "phone": "(657) 865-7552",
            "email": "Candelario88@gmail.com"
        },
        {
            "id": "47122353",
            "name": "Abel Quitzon",
            "phone": "(657) 984-4352",
            "email": "Abel88@live.com"
        },
        {
            "id": "76422423",
            "name": "Elliott Wolf",
            "phone": "(657) 984-4352",
            "email": "Elliott88@yahoo.com"
        }
    ]
}